{
  "summary": {
    "analyze_sec": "",
    "backend": "python",
    "buses": "",
    "case_name": "case118_ieee",
    "case_stem": "pglib_opf_case118_ieee",
    "compute": "fp64",
    "dump_case_name": "",
    "elapsed_sec": 0.011132372543215752,
    "final_mismatch": 6.14822223325176e-11,
    "implementation": "pypower",
    "iterations": 4,
    "jacobian": "pypower",
    "max_abs_v_delta_from_v0": "",
    "measurement_mode": "end2end",
    "pq": "",
    "profile": "pypower",
    "pv": "",
    "repeat_idx": 9,
    "solve_sec": "",
    "source_profile": "pypower",
    "success": true
  },
  "timing_entries": []
}
