{
  "summary": {
    "CUDA.analyze.cudss32.analysis.avg_sec": 0.127414,
    "CUDA.analyze.cudss32.analysis.count": 1,
    "CUDA.analyze.cudss32.analysis.total_sec": 0.127414,
    "CUDA.analyze.cudss32.setup.avg_sec": 0.001672,
    "CUDA.analyze.cudss32.setup.count": 1,
    "CUDA.analyze.cudss32.setup.total_sec": 0.001672,
    "CUDA.solve.factorization32.avg_sec": 0.00292,
    "CUDA.solve.factorization32.count": 1,
    "CUDA.solve.factorization32.total_sec": 0.00292,
    "CUDA.solve.refactorization32.avg_sec": 0.002823,
    "CUDA.solve.refactorization32.count": 5,
    "CUDA.solve.refactorization32.total_sec": 0.014115,
    "CUDA.solve.rhsPrepare.avg_sec": 0.0004391666666667,
    "CUDA.solve.rhsPrepare.count": 6,
    "CUDA.solve.rhsPrepare.total_sec": 0.002635,
    "CUDA.solve.solve32.avg_sec": 0.000993,
    "CUDA.solve.solve32.count": 6,
    "CUDA.solve.solve32.total_sec": 0.005958,
    "NR.analyze.jacobian_builder.avg_sec": 0.030721,
    "NR.analyze.jacobian_builder.count": 1,
    "NR.analyze.jacobian_builder.total_sec": 0.030721,
    "NR.analyze.linear_solve.avg_sec": 0.129093,
    "NR.analyze.linear_solve.count": 1,
    "NR.analyze.linear_solve.total_sec": 0.129093,
    "NR.analyze.storage_prepare.avg_sec": 0.003176,
    "NR.analyze.storage_prepare.count": 1,
    "NR.analyze.storage_prepare.total_sec": 0.003176,
    "NR.analyze.total.avg_sec": 0.162995,
    "NR.analyze.total.count": 1,
    "NR.analyze.total.total_sec": 0.162995,
    "NR.iteration.jacobian.avg_sec": 0.0001306666666667,
    "NR.iteration.jacobian.count": 6,
    "NR.iteration.jacobian.total_sec": 0.000784,
    "NR.iteration.linear_solve.avg_sec": 0.004303333333333,
    "NR.iteration.linear_solve.count": 6,
    "NR.iteration.linear_solve.total_sec": 0.02582,
    "NR.iteration.mismatch.avg_sec": 0.0004918571428571,
    "NR.iteration.mismatch.count": 7,
    "NR.iteration.mismatch.total_sec": 0.003443,
    "NR.iteration.total.avg_sec": 0.004335714285714,
    "NR.iteration.total.count": 7,
    "NR.iteration.total.total_sec": 0.03035,
    "NR.iteration.voltage_update.avg_sec": 4.85e-05,
    "NR.iteration.voltage_update.count": 6,
    "NR.iteration.voltage_update.total_sec": 0.000291,
    "NR.solve.download.avg_sec": 0.000471,
    "NR.solve.download.count": 1,
    "NR.solve.download.total_sec": 0.000471,
    "NR.solve.total.avg_sec": 0.03786,
    "NR.solve.total.count": 1,
    "NR.solve.total.total_sec": 0.03786,
    "NR.solve.upload.avg_sec": 0.007035,
    "NR.solve.upload.count": 1,
    "NR.solve.upload.total_sec": 0.007035,
    "analyze_sec": 0.163,
    "backend": "cuda",
    "buses": 70000,
    "case_name": "case_ACTIVSg70k",
    "compute": "mixed",
    "dump_case_name": "case_ACTIVSg70k",
    "elapsed_sec": 0.200863,
    "final_mismatch": 5.052429587266e-09,
    "implementation": "cuda_vertex",
    "iterations": 7,
    "jacobian": "vertex_based",
    "max_abs_v_delta_from_v0": 0.08741618909516,
    "measurement_mode": "operators",
    "pq": 64105,
    "profile": "cuda_vertex",
    "pv": 5894,
    "repeat_idx": 7,
    "solve_sec": 0.037862,
    "source_profile": "cuda_mixed_vertex",
    "success": true
  },
  "timing_entries": [
    {
      "avg_sec": 0.127414,
      "count": 1,
      "name": "CUDA.analyze.cudss32.analysis",
      "total_sec": 0.127414
    },
    {
      "avg_sec": 0.001672,
      "count": 1,
      "name": "CUDA.analyze.cudss32.setup",
      "total_sec": 0.001672
    },
    {
      "avg_sec": 0.00292,
      "count": 1,
      "name": "CUDA.solve.factorization32",
      "total_sec": 0.00292
    },
    {
      "avg_sec": 0.002823,
      "count": 5,
      "name": "CUDA.solve.refactorization32",
      "total_sec": 0.014115
    },
    {
      "avg_sec": 0.0004391666666667,
      "count": 6,
      "name": "CUDA.solve.rhsPrepare",
      "total_sec": 0.002635
    },
    {
      "avg_sec": 0.000993,
      "count": 6,
      "name": "CUDA.solve.solve32",
      "total_sec": 0.005958
    },
    {
      "avg_sec": 0.030721,
      "count": 1,
      "name": "NR.analyze.jacobian_builder",
      "total_sec": 0.030721
    },
    {
      "avg_sec": 0.129093,
      "count": 1,
      "name": "NR.analyze.linear_solve",
      "total_sec": 0.129093
    },
    {
      "avg_sec": 0.003176,
      "count": 1,
      "name": "NR.analyze.storage_prepare",
      "total_sec": 0.003176
    },
    {
      "avg_sec": 0.162995,
      "count": 1,
      "name": "NR.analyze.total",
      "total_sec": 0.162995
    },
    {
      "avg_sec": 0.0001306666666667,
      "count": 6,
      "name": "NR.iteration.jacobian",
      "total_sec": 0.000784
    },
    {
      "avg_sec": 0.004303333333333,
      "count": 6,
      "name": "NR.iteration.linear_solve",
      "total_sec": 0.02582
    },
    {
      "avg_sec": 0.0004918571428571,
      "count": 7,
      "name": "NR.iteration.mismatch",
      "total_sec": 0.003443
    },
    {
      "avg_sec": 0.004335714285714,
      "count": 7,
      "name": "NR.iteration.total",
      "total_sec": 0.03035
    },
    {
      "avg_sec": 4.85e-05,
      "count": 6,
      "name": "NR.iteration.voltage_update",
      "total_sec": 0.000291
    },
    {
      "avg_sec": 0.000471,
      "count": 1,
      "name": "NR.solve.download",
      "total_sec": 0.000471
    },
    {
      "avg_sec": 0.03786,
      "count": 1,
      "name": "NR.solve.total",
      "total_sec": 0.03786
    },
    {
      "avg_sec": 0.007035,
      "count": 1,
      "name": "NR.solve.upload",
      "total_sec": 0.007035
    }
  ]
}
