{
  "summary": {
    "CUDA.analyze.cudss32.analysis.avg_sec": 0.047972,
    "CUDA.analyze.cudss32.analysis.count": 1,
    "CUDA.analyze.cudss32.analysis.total_sec": 0.047972,
    "CUDA.analyze.cudss32.setup.avg_sec": 0.001605,
    "CUDA.analyze.cudss32.setup.count": 1,
    "CUDA.analyze.cudss32.setup.total_sec": 0.001605,
    "CUDA.solve.factorization32.avg_sec": 0.001267,
    "CUDA.solve.factorization32.count": 1,
    "CUDA.solve.factorization32.total_sec": 0.001267,
    "CUDA.solve.refactorization32.avg_sec": 0.001156,
    "CUDA.solve.refactorization32.count": 4,
    "CUDA.solve.refactorization32.total_sec": 0.004624,
    "CUDA.solve.rhsPrepare.avg_sec": 0.000184,
    "CUDA.solve.rhsPrepare.count": 5,
    "CUDA.solve.rhsPrepare.total_sec": 0.00092,
    "CUDA.solve.solve32.avg_sec": 0.0004354,
    "CUDA.solve.solve32.count": 5,
    "CUDA.solve.solve32.total_sec": 0.002177,
    "NR.analyze.jacobian_builder.avg_sec": 0.008533,
    "NR.analyze.jacobian_builder.count": 1,
    "NR.analyze.jacobian_builder.total_sec": 0.008533,
    "NR.analyze.linear_solve.avg_sec": 0.049581,
    "NR.analyze.linear_solve.count": 1,
    "NR.analyze.linear_solve.total_sec": 0.049581,
    "NR.analyze.storage_prepare.avg_sec": 0.001588,
    "NR.analyze.storage_prepare.count": 1,
    "NR.analyze.storage_prepare.total_sec": 0.001588,
    "NR.analyze.total.avg_sec": 0.059705,
    "NR.analyze.total.count": 1,
    "NR.analyze.total.total_sec": 0.059705,
    "NR.iteration.jacobian.avg_sec": 2.5e-05,
    "NR.iteration.jacobian.count": 5,
    "NR.iteration.jacobian.total_sec": 0.000125,
    "NR.iteration.linear_solve.avg_sec": 0.0018054,
    "NR.iteration.linear_solve.count": 5,
    "NR.iteration.linear_solve.total_sec": 0.009027,
    "NR.iteration.mismatch.avg_sec": 0.0002245,
    "NR.iteration.mismatch.count": 6,
    "NR.iteration.mismatch.total_sec": 0.001347,
    "NR.iteration.total.avg_sec": 0.001776666666667,
    "NR.iteration.total.count": 6,
    "NR.iteration.total.total_sec": 0.01066,
    "NR.iteration.voltage_update.avg_sec": 3.04e-05,
    "NR.iteration.voltage_update.count": 5,
    "NR.iteration.voltage_update.total_sec": 0.000152,
    "NR.solve.download.avg_sec": 0.000199,
    "NR.solve.download.count": 1,
    "NR.solve.download.total_sec": 0.000199,
    "NR.solve.total.avg_sec": 0.012188,
    "NR.solve.total.count": 1,
    "NR.solve.total.total_sec": 0.012188,
    "NR.solve.upload.avg_sec": 0.001326,
    "NR.solve.upload.count": 1,
    "NR.solve.upload.total_sec": 0.001326,
    "analyze_sec": 0.059707,
    "backend": "cuda",
    "buses": 20758,
    "case_name": "Base_West_Interconnect_121GW",
    "compute": "mixed",
    "dump_case_name": "Base_West_Interconnect_121GW",
    "elapsed_sec": 0.071896,
    "final_mismatch": 1.608815575473e-10,
    "implementation": "cuda_edge",
    "iterations": 6,
    "jacobian": "edge_based",
    "max_abs_v_delta_from_v0": 0.04032063151797,
    "measurement_mode": "operators",
    "pq": 19991,
    "profile": "cuda_edge",
    "pv": 766,
    "repeat_idx": 2,
    "solve_sec": 0.012189,
    "source_profile": "cuda_mixed_edge",
    "success": true
  },
  "timing_entries": [
    {
      "avg_sec": 0.047972,
      "count": 1,
      "name": "CUDA.analyze.cudss32.analysis",
      "total_sec": 0.047972
    },
    {
      "avg_sec": 0.001605,
      "count": 1,
      "name": "CUDA.analyze.cudss32.setup",
      "total_sec": 0.001605
    },
    {
      "avg_sec": 0.001267,
      "count": 1,
      "name": "CUDA.solve.factorization32",
      "total_sec": 0.001267
    },
    {
      "avg_sec": 0.001156,
      "count": 4,
      "name": "CUDA.solve.refactorization32",
      "total_sec": 0.004624
    },
    {
      "avg_sec": 0.000184,
      "count": 5,
      "name": "CUDA.solve.rhsPrepare",
      "total_sec": 0.00092
    },
    {
      "avg_sec": 0.0004354,
      "count": 5,
      "name": "CUDA.solve.solve32",
      "total_sec": 0.002177
    },
    {
      "avg_sec": 0.008533,
      "count": 1,
      "name": "NR.analyze.jacobian_builder",
      "total_sec": 0.008533
    },
    {
      "avg_sec": 0.049581,
      "count": 1,
      "name": "NR.analyze.linear_solve",
      "total_sec": 0.049581
    },
    {
      "avg_sec": 0.001588,
      "count": 1,
      "name": "NR.analyze.storage_prepare",
      "total_sec": 0.001588
    },
    {
      "avg_sec": 0.059705,
      "count": 1,
      "name": "NR.analyze.total",
      "total_sec": 0.059705
    },
    {
      "avg_sec": 2.5e-05,
      "count": 5,
      "name": "NR.iteration.jacobian",
      "total_sec": 0.000125
    },
    {
      "avg_sec": 0.0018054,
      "count": 5,
      "name": "NR.iteration.linear_solve",
      "total_sec": 0.009027
    },
    {
      "avg_sec": 0.0002245,
      "count": 6,
      "name": "NR.iteration.mismatch",
      "total_sec": 0.001347
    },
    {
      "avg_sec": 0.001776666666667,
      "count": 6,
      "name": "NR.iteration.total",
      "total_sec": 0.01066
    },
    {
      "avg_sec": 3.04e-05,
      "count": 5,
      "name": "NR.iteration.voltage_update",
      "total_sec": 0.000152
    },
    {
      "avg_sec": 0.000199,
      "count": 1,
      "name": "NR.solve.download",
      "total_sec": 0.000199
    },
    {
      "avg_sec": 0.012188,
      "count": 1,
      "name": "NR.solve.total",
      "total_sec": 0.012188
    },
    {
      "avg_sec": 0.001326,
      "count": 1,
      "name": "NR.solve.upload",
      "total_sec": 0.001326
    }
  ]
}
