{
  "summary": {
    "CUDA.analyze.cudss64.analysis.avg_sec": 0.12925,
    "CUDA.analyze.cudss64.analysis.count": 1,
    "CUDA.analyze.cudss64.analysis.total_sec": 0.12925,
    "CUDA.analyze.cudss64.setup.avg_sec": 0.001978,
    "CUDA.analyze.cudss64.setup.count": 1,
    "CUDA.analyze.cudss64.setup.total_sec": 0.001978,
    "CUDA.solve.factorization64.avg_sec": 0.004964,
    "CUDA.solve.factorization64.count": 1,
    "CUDA.solve.factorization64.total_sec": 0.004964,
    "CUDA.solve.refactorization64.avg_sec": 0.0048322,
    "CUDA.solve.refactorization64.count": 5,
    "CUDA.solve.refactorization64.total_sec": 0.024161,
    "CUDA.solve.rhsPrepare64.avg_sec": 0.0002146666666667,
    "CUDA.solve.rhsPrepare64.count": 6,
    "CUDA.solve.rhsPrepare64.total_sec": 0.001288,
    "CUDA.solve.solve64.avg_sec": 0.001516166666667,
    "CUDA.solve.solve64.count": 6,
    "CUDA.solve.solve64.total_sec": 0.009097,
    "NR.analyze.jacobian_builder.avg_sec": 0.029855,
    "NR.analyze.jacobian_builder.count": 1,
    "NR.analyze.jacobian_builder.total_sec": 0.029855,
    "NR.analyze.linear_solve.avg_sec": 0.131301,
    "NR.analyze.linear_solve.count": 1,
    "NR.analyze.linear_solve.total_sec": 0.131301,
    "NR.analyze.storage_prepare.avg_sec": 0.002298,
    "NR.analyze.storage_prepare.count": 1,
    "NR.analyze.storage_prepare.total_sec": 0.002298,
    "NR.analyze.total.avg_sec": 0.163459,
    "NR.analyze.total.count": 1,
    "NR.analyze.total.total_sec": 0.163459,
    "NR.iteration.jacobian.avg_sec": 0.0001595,
    "NR.iteration.jacobian.count": 6,
    "NR.iteration.jacobian.total_sec": 0.000957,
    "NR.iteration.linear_solve.avg_sec": 0.006602333333333,
    "NR.iteration.linear_solve.count": 6,
    "NR.iteration.linear_solve.total_sec": 0.039614,
    "NR.iteration.mismatch.avg_sec": 0.0002468571428571,
    "NR.iteration.mismatch.count": 7,
    "NR.iteration.mismatch.total_sec": 0.001728,
    "NR.iteration.total.avg_sec": 0.006084857142857,
    "NR.iteration.total.count": 7,
    "NR.iteration.total.total_sec": 0.042594,
    "NR.iteration.voltage_update.avg_sec": 4.733333333333e-05,
    "NR.iteration.voltage_update.count": 6,
    "NR.iteration.voltage_update.total_sec": 0.000284,
    "NR.solve.download.avg_sec": 0.000201,
    "NR.solve.download.count": 1,
    "NR.solve.download.total_sec": 0.000201,
    "NR.solve.total.avg_sec": 0.04526,
    "NR.solve.total.count": 1,
    "NR.solve.total.total_sec": 0.04526,
    "NR.solve.upload.avg_sec": 0.002461,
    "NR.solve.upload.count": 1,
    "NR.solve.upload.total_sec": 0.002461,
    "analyze_sec": 0.163463,
    "backend": "cuda",
    "buses": 70000,
    "case_name": "case_ACTIVSg70k",
    "compute": "fp64",
    "dump_case_name": "case_ACTIVSg70k",
    "elapsed_sec": 0.208726,
    "final_mismatch": 2.07305550411e-11,
    "implementation": "cuda_fp64_edge",
    "iterations": 7,
    "jacobian": "edge_based",
    "max_abs_v_delta_from_v0": 0.08741618894454,
    "measurement_mode": "operators",
    "pq": 64105,
    "profile": "cuda_fp64_edge",
    "pv": 5894,
    "repeat_idx": 3,
    "solve_sec": 0.045262,
    "source_profile": "cuda_fp64_edge",
    "success": true
  },
  "timing_entries": [
    {
      "avg_sec": 0.12925,
      "count": 1,
      "name": "CUDA.analyze.cudss64.analysis",
      "total_sec": 0.12925
    },
    {
      "avg_sec": 0.001978,
      "count": 1,
      "name": "CUDA.analyze.cudss64.setup",
      "total_sec": 0.001978
    },
    {
      "avg_sec": 0.004964,
      "count": 1,
      "name": "CUDA.solve.factorization64",
      "total_sec": 0.004964
    },
    {
      "avg_sec": 0.0048322,
      "count": 5,
      "name": "CUDA.solve.refactorization64",
      "total_sec": 0.024161
    },
    {
      "avg_sec": 0.0002146666666667,
      "count": 6,
      "name": "CUDA.solve.rhsPrepare64",
      "total_sec": 0.001288
    },
    {
      "avg_sec": 0.001516166666667,
      "count": 6,
      "name": "CUDA.solve.solve64",
      "total_sec": 0.009097
    },
    {
      "avg_sec": 0.029855,
      "count": 1,
      "name": "NR.analyze.jacobian_builder",
      "total_sec": 0.029855
    },
    {
      "avg_sec": 0.131301,
      "count": 1,
      "name": "NR.analyze.linear_solve",
      "total_sec": 0.131301
    },
    {
      "avg_sec": 0.002298,
      "count": 1,
      "name": "NR.analyze.storage_prepare",
      "total_sec": 0.002298
    },
    {
      "avg_sec": 0.163459,
      "count": 1,
      "name": "NR.analyze.total",
      "total_sec": 0.163459
    },
    {
      "avg_sec": 0.0001595,
      "count": 6,
      "name": "NR.iteration.jacobian",
      "total_sec": 0.000957
    },
    {
      "avg_sec": 0.006602333333333,
      "count": 6,
      "name": "NR.iteration.linear_solve",
      "total_sec": 0.039614
    },
    {
      "avg_sec": 0.0002468571428571,
      "count": 7,
      "name": "NR.iteration.mismatch",
      "total_sec": 0.001728
    },
    {
      "avg_sec": 0.006084857142857,
      "count": 7,
      "name": "NR.iteration.total",
      "total_sec": 0.042594
    },
    {
      "avg_sec": 4.733333333333e-05,
      "count": 6,
      "name": "NR.iteration.voltage_update",
      "total_sec": 0.000284
    },
    {
      "avg_sec": 0.000201,
      "count": 1,
      "name": "NR.solve.download",
      "total_sec": 0.000201
    },
    {
      "avg_sec": 0.04526,
      "count": 1,
      "name": "NR.solve.total",
      "total_sec": 0.04526
    },
    {
      "avg_sec": 0.002461,
      "count": 1,
      "name": "NR.solve.upload",
      "total_sec": 0.002461
    }
  ]
}
