{
  "summary": {
    "CUDA.analyze.cudss64.analysis.avg_sec": 0.019975,
    "CUDA.analyze.cudss64.analysis.count": 1,
    "CUDA.analyze.cudss64.analysis.total_sec": 0.019975,
    "CUDA.analyze.cudss64.setup.avg_sec": 0.001662,
    "CUDA.analyze.cudss64.setup.count": 1,
    "CUDA.analyze.cudss64.setup.total_sec": 0.001662,
    "CUDA.solve.factorization64.avg_sec": 0.000871,
    "CUDA.solve.factorization64.count": 1,
    "CUDA.solve.factorization64.total_sec": 0.000871,
    "CUDA.solve.refactorization64.avg_sec": 0.000768,
    "CUDA.solve.refactorization64.count": 3,
    "CUDA.solve.refactorization64.total_sec": 0.002304,
    "CUDA.solve.rhsPrepare64.avg_sec": 2.9e-05,
    "CUDA.solve.rhsPrepare64.count": 4,
    "CUDA.solve.rhsPrepare64.total_sec": 0.000116,
    "CUDA.solve.solve64.avg_sec": 0.00036525,
    "CUDA.solve.solve64.count": 4,
    "CUDA.solve.solve64.total_sec": 0.001461,
    "NR.analyze.jacobian_builder.avg_sec": 0.003151,
    "NR.analyze.jacobian_builder.count": 1,
    "NR.analyze.jacobian_builder.total_sec": 0.003151,
    "NR.analyze.linear_solve.avg_sec": 0.021641,
    "NR.analyze.linear_solve.count": 1,
    "NR.analyze.linear_solve.total_sec": 0.021641,
    "NR.analyze.storage_prepare.avg_sec": 0.000447,
    "NR.analyze.storage_prepare.count": 1,
    "NR.analyze.storage_prepare.total_sec": 0.000447,
    "NR.analyze.total.avg_sec": 0.025241,
    "NR.analyze.total.count": 1,
    "NR.analyze.total.total_sec": 0.025241,
    "NR.iteration.jacobian.avg_sec": 3.75e-05,
    "NR.iteration.jacobian.count": 4,
    "NR.iteration.jacobian.total_sec": 0.00015,
    "NR.iteration.linear_solve.avg_sec": 0.00119,
    "NR.iteration.linear_solve.count": 4,
    "NR.iteration.linear_solve.total_sec": 0.00476,
    "NR.iteration.mismatch.avg_sec": 4.08e-05,
    "NR.iteration.mismatch.count": 5,
    "NR.iteration.mismatch.total_sec": 0.000204,
    "NR.iteration.total.avg_sec": 0.0010406,
    "NR.iteration.total.count": 5,
    "NR.iteration.total.total_sec": 0.005203,
    "NR.iteration.voltage_update.avg_sec": 2.05e-05,
    "NR.iteration.voltage_update.count": 4,
    "NR.iteration.voltage_update.total_sec": 8.2e-05,
    "NR.solve.download.avg_sec": 3.2e-05,
    "NR.solve.download.count": 1,
    "NR.solve.download.total_sec": 3.2e-05,
    "NR.solve.total.avg_sec": 0.005544,
    "NR.solve.total.count": 1,
    "NR.solve.total.total_sec": 0.005544,
    "NR.solve.upload.avg_sec": 0.000305,
    "NR.solve.upload.count": 1,
    "NR.solve.upload.total_sec": 0.000305,
    "analyze_sec": 0.025242,
    "backend": "cuda",
    "buses": 5658,
    "case_name": "Base_Florida_42GW",
    "compute": "fp64",
    "dump_case_name": "Base_Florida_42GW",
    "elapsed_sec": 0.030787,
    "final_mismatch": 5.055567076084e-12,
    "implementation": "cuda_fp64_edge",
    "iterations": 5,
    "jacobian": "edge_based",
    "max_abs_v_delta_from_v0": 0.05033550758131,
    "measurement_mode": "operators",
    "pq": 5553,
    "profile": "cuda_fp64_edge",
    "pv": 104,
    "repeat_idx": 0,
    "solve_sec": 0.005545,
    "source_profile": "cuda_fp64_edge",
    "success": true
  },
  "timing_entries": [
    {
      "avg_sec": 0.019975,
      "count": 1,
      "name": "CUDA.analyze.cudss64.analysis",
      "total_sec": 0.019975
    },
    {
      "avg_sec": 0.001662,
      "count": 1,
      "name": "CUDA.analyze.cudss64.setup",
      "total_sec": 0.001662
    },
    {
      "avg_sec": 0.000871,
      "count": 1,
      "name": "CUDA.solve.factorization64",
      "total_sec": 0.000871
    },
    {
      "avg_sec": 0.000768,
      "count": 3,
      "name": "CUDA.solve.refactorization64",
      "total_sec": 0.002304
    },
    {
      "avg_sec": 2.9e-05,
      "count": 4,
      "name": "CUDA.solve.rhsPrepare64",
      "total_sec": 0.000116
    },
    {
      "avg_sec": 0.00036525,
      "count": 4,
      "name": "CUDA.solve.solve64",
      "total_sec": 0.001461
    },
    {
      "avg_sec": 0.003151,
      "count": 1,
      "name": "NR.analyze.jacobian_builder",
      "total_sec": 0.003151
    },
    {
      "avg_sec": 0.021641,
      "count": 1,
      "name": "NR.analyze.linear_solve",
      "total_sec": 0.021641
    },
    {
      "avg_sec": 0.000447,
      "count": 1,
      "name": "NR.analyze.storage_prepare",
      "total_sec": 0.000447
    },
    {
      "avg_sec": 0.025241,
      "count": 1,
      "name": "NR.analyze.total",
      "total_sec": 0.025241
    },
    {
      "avg_sec": 3.75e-05,
      "count": 4,
      "name": "NR.iteration.jacobian",
      "total_sec": 0.00015
    },
    {
      "avg_sec": 0.00119,
      "count": 4,
      "name": "NR.iteration.linear_solve",
      "total_sec": 0.00476
    },
    {
      "avg_sec": 4.08e-05,
      "count": 5,
      "name": "NR.iteration.mismatch",
      "total_sec": 0.000204
    },
    {
      "avg_sec": 0.0010406,
      "count": 5,
      "name": "NR.iteration.total",
      "total_sec": 0.005203
    },
    {
      "avg_sec": 2.05e-05,
      "count": 4,
      "name": "NR.iteration.voltage_update",
      "total_sec": 8.2e-05
    },
    {
      "avg_sec": 3.2e-05,
      "count": 1,
      "name": "NR.solve.download",
      "total_sec": 3.2e-05
    },
    {
      "avg_sec": 0.005544,
      "count": 1,
      "name": "NR.solve.total",
      "total_sec": 0.005544
    },
    {
      "avg_sec": 0.000305,
      "count": 1,
      "name": "NR.solve.upload",
      "total_sec": 0.000305
    }
  ]
}
