{
  "summary": {
    "CUDA.analyze.cudss32.analysis.avg_sec": 0.014837,
    "CUDA.analyze.cudss32.analysis.count": 1,
    "CUDA.analyze.cudss32.analysis.total_sec": 0.014837,
    "CUDA.analyze.cudss32.setup.avg_sec": 0.001682,
    "CUDA.analyze.cudss32.setup.count": 1,
    "CUDA.analyze.cudss32.setup.total_sec": 0.001682,
    "CUDA.solve.factorization32.avg_sec": 0.000314,
    "CUDA.solve.factorization32.count": 1,
    "CUDA.solve.factorization32.total_sec": 0.000314,
    "CUDA.solve.refactorization32.avg_sec": 0.000181,
    "CUDA.solve.refactorization32.count": 4,
    "CUDA.solve.refactorization32.total_sec": 0.000724,
    "CUDA.solve.rhsPrepare.avg_sec": 2.18e-05,
    "CUDA.solve.rhsPrepare.count": 5,
    "CUDA.solve.rhsPrepare.total_sec": 0.000109,
    "CUDA.solve.solve32.avg_sec": 0.0001282,
    "CUDA.solve.solve32.count": 5,
    "CUDA.solve.solve32.total_sec": 0.000641,
    "NR.analyze.jacobian_builder.avg_sec": 0.000618,
    "NR.analyze.jacobian_builder.count": 1,
    "NR.analyze.jacobian_builder.total_sec": 0.000618,
    "NR.analyze.linear_solve.avg_sec": 0.016522,
    "NR.analyze.linear_solve.count": 1,
    "NR.analyze.linear_solve.total_sec": 0.016522,
    "NR.analyze.storage_prepare.avg_sec": 0.000343,
    "NR.analyze.storage_prepare.count": 1,
    "NR.analyze.storage_prepare.total_sec": 0.000343,
    "NR.analyze.total.avg_sec": 0.017486,
    "NR.analyze.total.count": 1,
    "NR.analyze.total.total_sec": 0.017486,
    "NR.iteration.jacobian.avg_sec": 1.26e-05,
    "NR.iteration.jacobian.count": 5,
    "NR.iteration.jacobian.total_sec": 6.3e-05,
    "NR.iteration.linear_solve.avg_sec": 0.0003592,
    "NR.iteration.linear_solve.count": 5,
    "NR.iteration.linear_solve.total_sec": 0.001796,
    "NR.iteration.mismatch.avg_sec": 3.666666666667e-05,
    "NR.iteration.mismatch.count": 6,
    "NR.iteration.mismatch.total_sec": 0.00022,
    "NR.iteration.total.avg_sec": 0.0003656666666667,
    "NR.iteration.total.count": 6,
    "NR.iteration.total.total_sec": 0.002194,
    "NR.iteration.voltage_update.avg_sec": 2.12e-05,
    "NR.iteration.voltage_update.count": 5,
    "NR.iteration.voltage_update.total_sec": 0.000106,
    "NR.solve.download.avg_sec": 2.9e-05,
    "NR.solve.download.count": 1,
    "NR.solve.download.total_sec": 2.9e-05,
    "NR.solve.total.avg_sec": 0.002358,
    "NR.solve.total.count": 1,
    "NR.solve.total.total_sec": 0.002358,
    "NR.solve.upload.avg_sec": 0.000131,
    "NR.solve.upload.count": 1,
    "NR.solve.upload.total_sec": 0.000131,
    "analyze_sec": 0.017487,
    "backend": "cuda",
    "buses": 1354,
    "case_name": "case1354_pegase",
    "compute": "mixed",
    "dump_case_name": "case1354_pegase",
    "elapsed_sec": 0.019847,
    "final_mismatch": 5.743627795596e-12,
    "implementation": "cuda_edge",
    "iterations": 6,
    "jacobian": "edge_based",
    "max_abs_v_delta_from_v0": 0.9675246266078,
    "measurement_mode": "operators",
    "pq": 1094,
    "profile": "cuda_edge",
    "pv": 259,
    "repeat_idx": 0,
    "solve_sec": 0.002359,
    "source_profile": "cuda_mixed_edge",
    "success": true
  },
  "timing_entries": [
    {
      "avg_sec": 0.014837,
      "count": 1,
      "name": "CUDA.analyze.cudss32.analysis",
      "total_sec": 0.014837
    },
    {
      "avg_sec": 0.001682,
      "count": 1,
      "name": "CUDA.analyze.cudss32.setup",
      "total_sec": 0.001682
    },
    {
      "avg_sec": 0.000314,
      "count": 1,
      "name": "CUDA.solve.factorization32",
      "total_sec": 0.000314
    },
    {
      "avg_sec": 0.000181,
      "count": 4,
      "name": "CUDA.solve.refactorization32",
      "total_sec": 0.000724
    },
    {
      "avg_sec": 2.18e-05,
      "count": 5,
      "name": "CUDA.solve.rhsPrepare",
      "total_sec": 0.000109
    },
    {
      "avg_sec": 0.0001282,
      "count": 5,
      "name": "CUDA.solve.solve32",
      "total_sec": 0.000641
    },
    {
      "avg_sec": 0.000618,
      "count": 1,
      "name": "NR.analyze.jacobian_builder",
      "total_sec": 0.000618
    },
    {
      "avg_sec": 0.016522,
      "count": 1,
      "name": "NR.analyze.linear_solve",
      "total_sec": 0.016522
    },
    {
      "avg_sec": 0.000343,
      "count": 1,
      "name": "NR.analyze.storage_prepare",
      "total_sec": 0.000343
    },
    {
      "avg_sec": 0.017486,
      "count": 1,
      "name": "NR.analyze.total",
      "total_sec": 0.017486
    },
    {
      "avg_sec": 1.26e-05,
      "count": 5,
      "name": "NR.iteration.jacobian",
      "total_sec": 6.3e-05
    },
    {
      "avg_sec": 0.0003592,
      "count": 5,
      "name": "NR.iteration.linear_solve",
      "total_sec": 0.001796
    },
    {
      "avg_sec": 3.666666666667e-05,
      "count": 6,
      "name": "NR.iteration.mismatch",
      "total_sec": 0.00022
    },
    {
      "avg_sec": 0.0003656666666667,
      "count": 6,
      "name": "NR.iteration.total",
      "total_sec": 0.002194
    },
    {
      "avg_sec": 2.12e-05,
      "count": 5,
      "name": "NR.iteration.voltage_update",
      "total_sec": 0.000106
    },
    {
      "avg_sec": 2.9e-05,
      "count": 1,
      "name": "NR.solve.download",
      "total_sec": 2.9e-05
    },
    {
      "avg_sec": 0.002358,
      "count": 1,
      "name": "NR.solve.total",
      "total_sec": 0.002358
    },
    {
      "avg_sec": 0.000131,
      "count": 1,
      "name": "NR.solve.upload",
      "total_sec": 0.000131
    }
  ]
}
